README.md
setup.py
aiotraceroute/__init__.py
aiotraceroute/aiotraceroute.py
aiotraceroute.egg-info/PKG-INFO
aiotraceroute.egg-info/SOURCES.txt
aiotraceroute.egg-info/dependency_links.txt
aiotraceroute.egg-info/requires.txt
aiotraceroute.egg-info/top_level.txt
tests/__init__.py
tests/context.py
tests/test_aiotraceroute.py