Metadata-Version: 2.1
Name: aiotraceroute
Version: 1.0.0
Summary: Asynchronous traceroute in python
Home-page: https://github.com/NicoAdrian/aiotraceroute
Author: Nicolas Adrian
Author-email: nicolasadrian3@gmail.com
License: MIT
Keywords: traceroute,async,asyncio
Platform: UNKNOWN
